causaldynamics-0.1.1.dist-info/METADATA
causaldynamics-0.1.1.dist-info/WHEEL
causaldynamics-0.1.1.dist-info/entry_points.txt
causaldynamics-0.1.1.dist-info/licenses/LICENSE.txt
causaldynamics/__init__.py
causaldynamics/baselines/__init__.py
causaldynamics/baselines/ccm.py
causaldynamics/baselines/cuts.py
causaldynamics/baselines/dynotears.py
causaldynamics/baselines/neuralgc.py
causaldynamics/baselines/pcmci.py
causaldynamics/baselines/varlingam.py
causaldynamics/creator.py
causaldynamics/data_io.py
causaldynamics/idealized/XRO_indices_oras5.nc
causaldynamics/idealized/xro.py
causaldynamics/idealized/xro_utils.py
causaldynamics/initialization.py
causaldynamics/mlp.py
causaldynamics/plot.py
causaldynamics/scm.py
causaldynamics/score.py
causaldynamics/systems.py
causaldynamics/utils.py
causaldynamics-0.1.1.dist-info/RECORD
