Metadata-Version: 2.4
Name: causaldynamics
Version: 0.1.1
Summary: CausalDynamics: A large-scale benchmark for structural discovery of dynamical causal models
Author-Email: Benjamin Herdeanu <benjamin@kausable.ai>, Juan Nathaniel <jn2808@columbia.edu>, Johannes Haux <johannes@kausable.ai>
License-Expression: MIT
License-File: LICENSE.txt
Classifier: Programming Language :: Python :: 3
Classifier: Operating System :: OS Independent
Project-URL: Homepage, https://kausable.github.io/CausalDynamics
Project-URL: Issues, https://github.com/kausable/CausalDynamics/issues
Requires-Python: <3.11,>=3.10
Requires-Dist: numpy<2.0
Requires-Dist: dysts>=0.95
Requires-Dist: numba<=0.61.0
Requires-Dist: matplotlib>=3.10.1
Requires-Dist: seaborn>=0.13.2
Requires-Dist: jupyter>=1.1.1
Requires-Dist: ipywidgets>=8.1.5
Requires-Dist: jsonargparse>=4.38.0
Requires-Dist: jax>=0.5.3
Requires-Dist: black>=25.1.0
Requires-Dist: xarray>=2023.10.0
Requires-Dist: torch>=2.6.0
Requires-Dist: joblib>=1.4.2
Requires-Dist: scikit-learn>=1.6.1
Requires-Dist: jaxtyping>=0.3.1
Requires-Dist: statsmodels>=0.14.4
Requires-Dist: einops>=0.8.1
Requires-Dist: omegaconf>=2.3.0
Requires-Dist: sdeint>=0.3.0
Requires-Dist: zarr>=2.18.3
Requires-Dist: qgs>=1.0.0
Requires-Dist: sparse<=0.15.5
Requires-Dist: netcdf4>=1.7.2
